[
  {
    "id": "tr_q001",
    "question": "What architecture is introduced in the paper 'Attention Is All You Need'?",
    "ground_truth": "The Transformer architecture.",
    "difficulty": "easy",
    "category": "overview"
  },
  {
    "id": "tr_q002",
    "question": "What major neural network components does the Transformer eliminate?",
    "ground_truth": "Recurrence (RNNs) and convolutions (CNNs).",
    "difficulty": "easy",
    "category": "motivation"
  },
  {
    "id": "tr_q003",
    "question": "What mechanism is the Transformer based entirely upon?",
    "ground_truth": "Attention mechanisms, specifically self-attention.",
    "difficulty": "easy",
    "category": "architecture"
  },
  {
    "id": "tr_q004",
    "question": "What machine translation benchmark did the Transformer achieve 28.4 BLEU on?",
    "ground_truth": "WMT 2014 English-to-German translation.",
    "difficulty": "easy",
    "category": "results"
  },
  {
    "id": "tr_q005",
    "question": "What BLEU score did the Transformer achieve on WMT 2014 English-to-French translation?",
    "ground_truth": "41.0 BLEU.",
    "difficulty": "easy",
    "category": "results"
  },
  {
    "id": "tr_q006",
    "question": "How many encoder layers are used in the base Transformer model?",
    "ground_truth": "Six encoder layers.",
    "difficulty": "easy",
    "category": "architecture"
  },
  {
    "id": "tr_q007",
    "question": "How many decoder layers are used in the base Transformer model?",
    "ground_truth": "Six decoder layers.",
    "difficulty": "easy",
    "category": "architecture"
  },
  {
    "id": "tr_q008",
    "question": "What are the two main sub-layers in each encoder block?",
    "ground_truth": "Multi-head self-attention and position-wise feed-forward network.",
    "difficulty": "easy",
    "category": "architecture"
  },
  {
    "id": "tr_q009",
    "question": "What additional sub-layer exists in each decoder block?",
    "ground_truth": "Encoder-decoder attention (cross-attention).",
    "difficulty": "easy",
    "category": "architecture"
  },
  {
    "id": "tr_q010",
    "question": "Why is masking applied in the decoder self-attention layers?",
    "ground_truth": "To prevent positions from attending to future tokens during autoregressive generation.",
    "difficulty": "medium",
    "category": "decoder"
  },
  {
    "id": "tr_q011",
    "question": "What is the formula for Scaled Dot-Product Attention?",
    "ground_truth": "Attention(Q,K,V) = softmax(QK^T / sqrt(d_k))V.",
    "difficulty": "medium",
    "category": "attention"
  },
  {
    "id": "tr_q012",
    "question": "Why is the dot product scaled by sqrt(d_k)?",
    "ground_truth": "To prevent large dot-product values that would push softmax into regions with very small gradients.",
    "difficulty": "medium",
    "category": "attention"
  },
  {
    "id": "tr_q013",
    "question": "What is the purpose of Multi-Head Attention?",
    "ground_truth": "To allow the model to attend to information from different representation subspaces simultaneously.",
    "difficulty": "easy",
    "category": "attention"
  },
  {
    "id": "tr_q014",
    "question": "How many attention heads are used in the base Transformer?",
    "ground_truth": "Eight attention heads.",
    "difficulty": "easy",
    "category": "architecture"
  },
  {
    "id": "tr_q015",
    "question": "What is the value of d_model in the base Transformer?",
    "ground_truth": "512.",
    "difficulty": "easy",
    "category": "hyperparameters"
  },
  {
    "id": "tr_q016",
    "question": "What is the hidden dimension of the feed-forward network in the base Transformer?",
    "ground_truth": "2048.",
    "difficulty": "easy",
    "category": "hyperparameters"
  },
  {
    "id": "tr_q017",
    "question": "Why are positional encodings required in the Transformer?",
    "ground_truth": "Because the model contains neither recurrence nor convolution and therefore needs explicit position information.",
    "difficulty": "easy",
    "category": "positional_encoding"
  },
  {
    "id": "tr_q018",
    "question": "What type of positional encoding is primarily used in the paper?",
    "ground_truth": "Sinusoidal positional encoding using sine and cosine functions of different frequencies.",
    "difficulty": "easy",
    "category": "positional_encoding"
  },
  {
    "id": "tr_q019",
    "question": "Which optimizer is used to train the Transformer?",
    "ground_truth": "Adam optimizer.",
    "difficulty": "easy",
    "category": "training"
  },
  {
    "id": "tr_q020",
    "question": "What is the main conclusion of the paper?",
    "ground_truth": "Attention-only architectures can outperform recurrent and convolutional sequence models while training faster and enabling greater parallelization.",
    "difficulty": "easy",
    "category": "conclusion"
  },
  {
    "id": "tr_q021",
    "question": "What model is introduced in the paper 'Generative Adversarial Transformers'?",
    "ground_truth": "GANsformer (Generative Adversarial Transformer).",
    "difficulty": "easy",
    "category": "overview"
  },
  {
    "id": "tr_q022",
    "question": "What problem domain does GANsformer primarily target?",
    "ground_truth": "Visual generative modeling and image synthesis.",
    "difficulty": "easy",
    "category": "application"
  },
  {
    "id": "tr_q023",
    "question": "What key limitation of standard transformers in computer vision does GANsformer address?",
    "ground_truth": "Quadratic computational complexity caused by global self-attention.",
    "difficulty": "easy",
    "category": "motivation"
  },
  {
    "id": "tr_q024",
    "question": "What architectural structure is introduced to reduce attention complexity?",
    "ground_truth": "A Bipartite Transformer structure.",
    "difficulty": "easy",
    "category": "architecture"
  },
  {
    "id": "tr_q025",
    "question": "What are the two groups of nodes connected in the bipartite graph?",
    "ground_truth": "Latent variables and image feature representations.",
    "difficulty": "easy",
    "category": "architecture"
  },
  {
    "id": "tr_q026",
    "question": "How does GANsformer differ from standard self-attention?",
    "ground_truth": "It performs attention between latents and image features instead of all pairwise feature interactions.",
    "difficulty": "medium",
    "category": "attention"
  },
  {
    "id": "tr_q027",
    "question": "What are the two attention mechanisms proposed in GANsformer?",
    "ground_truth": "Simplex Attention and Duplex Attention.",
    "difficulty": "easy",
    "category": "attention"
  },
  {
    "id": "tr_q028",
    "question": "What is the main characteristic of Simplex Attention?",
    "ground_truth": "Information flows in a single direction.",
    "difficulty": "easy",
    "category": "attention"
  },
  {
    "id": "tr_q029",
    "question": "What is the main characteristic of Duplex Attention?",
    "ground_truth": "Information flows bidirectionally between latents and image features.",
    "difficulty": "easy",
    "category": "attention"
  },
  {
    "id": "tr_q030",
    "question": "What cognitive inspiration motivated the GANsformer design?",
    "ground_truth": "The interaction between top-down and bottom-up visual processing.",
    "difficulty": "medium",
    "category": "motivation"
  },
  {
    "id": "tr_q031",
    "question": "What complexity does the Bipartite Transformer achieve?",
    "ground_truth": "O(mn) complexity, where m is the number of latents and n is the number of image features.",
    "difficulty": "medium",
    "category": "efficiency"
  },
  {
    "id": "tr_q032",
    "question": "What complexity does standard self-attention have?",
    "ground_truth": "O(n²).",
    "difficulty": "easy",
    "category": "efficiency"
  },
  {
    "id": "tr_q033",
    "question": "How many latent variables are typically used in GANsformer?",
    "ground_truth": "Between 8 and 32 latent variables.",
    "difficulty": "easy",
    "category": "hyperparameters"
  },
  {
    "id": "tr_q034",
    "question": "Which famous GAN architecture inspired GANsformer's style modulation mechanism?",
    "ground_truth": "StyleGAN.",
    "difficulty": "easy",
    "category": "related_work"
  },
  {
    "id": "tr_q035",
    "question": "What integration mechanism replaces the standard additive transformer update?",
    "ground_truth": "Multiplicative integration using gain and bias modulation.",
    "difficulty": "medium",
    "category": "architecture"
  },
  {
    "id": "tr_q036",
    "question": "Why is multiplicative integration used in GANsformer?",
    "ground_truth": "To enable flexible region-based style modulation and improve generation quality.",
    "difficulty": "medium",
    "category": "design_choice"
  },
  {
    "id": "tr_q037",
    "question": "What role do latent variables play during image synthesis?",
    "ground_truth": "They attend to image regions and modulate feature generation in a spatially adaptive manner.",
    "difficulty": "medium",
    "category": "latent_space"
  },
  {
    "id": "tr_q038",
    "question": "What advantage does the multi-latent design provide over StyleGAN's single latent vector?",
    "ground_truth": "It enables compositional and region-specific control of generated scenes.",
    "difficulty": "medium",
    "category": "latent_space"
  },
  {
    "id": "tr_q039",
    "question": "What datasets were used to evaluate GANsformer?",
    "ground_truth": "CLEVR, LSUN-Bedroom, FFHQ, and Cityscapes.",
    "difficulty": "easy",
    "category": "experiments"
  },
  {
    "id": "tr_q040",
    "question": "What is the main conclusion of the paper?",
    "ground_truth": "Bipartite transformers can efficiently improve image generation quality, compositionality, interpretability, and data efficiency while maintaining scalable computation.",
    "difficulty": "medium",
    "category": "conclusion"
  },
  {
    "id": "tr_q041",
    "question": "What is the primary purpose of the Hugging Face Transformers library?",
    "ground_truth": "To provide a unified open-source framework for Transformer architectures and pretrained models.",
    "difficulty": "easy",
    "category": "overview"
  },
  {
    "id": "tr_q042",
    "question": "Which organization developed the Transformers library?",
    "ground_truth": "Hugging Face.",
    "difficulty": "easy",
    "category": "overview"
  },
  {
    "id": "tr_q043",
    "question": "What are the three core building blocks of every model in the Transformers library?",
    "ground_truth": "Tokenizer, Transformer, and Head.",
    "difficulty": "easy",
    "category": "architecture"
  },
  {
    "id": "tr_q044",
    "question": "What is the role of a tokenizer in the Transformers library?",
    "ground_truth": "To convert raw text into token IDs that can be processed by Transformer models.",
    "difficulty": "easy",
    "category": "tokenization"
  },
  {
    "id": "tr_q045",
    "question": "What is the role of the Transformer component in the library architecture?",
    "ground_truth": "To transform token IDs into contextualized embeddings.",
    "difficulty": "easy",
    "category": "architecture"
  },
  {
    "id": "tr_q046",
    "question": "What is the role of a head in the Transformers framework?",
    "ground_truth": "To convert contextual embeddings into task-specific predictions.",
    "difficulty": "easy",
    "category": "architecture"
  },
  {
    "id": "tr_q047",
    "question": "What unified API mechanism allows users to switch between different Transformer architectures?",
    "ground_truth": "The Auto classes such as AutoModel and AutoTokenizer.",
    "difficulty": "easy",
    "category": "api"
  },
  {
    "id": "tr_q048",
    "question": "What is the purpose of AutoModel?",
    "ground_truth": "To automatically instantiate the correct Transformer model from a pretrained checkpoint.",
    "difficulty": "easy",
    "category": "api"
  },
  {
    "id": "tr_q049",
    "question": "What is the purpose of AutoTokenizer?",
    "ground_truth": "To automatically load the tokenizer associated with a pretrained model.",
    "difficulty": "easy",
    "category": "api"
  },
  {
    "id": "tr_q050",
    "question": "Name three tokenizer algorithms supported by the library.",
    "ground_truth": "Examples include Byte-Pair Encoding (BPE), WordPiece, SentencePiece, Unigram LM, and Character tokenization.",
    "difficulty": "easy",
    "category": "tokenization"
  },
  {
    "id": "tr_q051",
    "question": "Which tokenizer is used by BERT according to the paper?",
    "ground_truth": "WordPiece.",
    "difficulty": "easy",
    "category": "tokenization"
  },
  {
    "id": "tr_q052",
    "question": "Which tokenizer is used by GPT-2 according to the paper?",
    "ground_truth": "Byte-Level BPE.",
    "difficulty": "easy",
    "category": "tokenization"
  },
  {
    "id": "tr_q053",
    "question": "What programming language was introduced for high-performance tokenization?",
    "ground_truth": "Rust.",
    "difficulty": "easy",
    "category": "implementation"
  },
  {
    "id": "tr_q054",
    "question": "What is the purpose of the Model Hub?",
    "ground_truth": "To distribute, share, discover, and reuse pretrained and fine-tuned Transformer models.",
    "difficulty": "easy",
    "category": "model_hub"
  },
  {
    "id": "tr_q055",
    "question": "What metadata document can accompany uploaded models to describe training details and limitations?",
    "ground_truth": "A Model Card.",
    "difficulty": "easy",
    "category": "model_hub"
  },
  {
    "id": "tr_q056",
    "question": "What deployment format is highlighted for achieving significant inference speedups?",
    "ground_truth": "ONNX (Open Neural Network Exchange).",
    "difficulty": "easy",
    "category": "deployment"
  },
  {
    "id": "tr_q057",
    "question": "Approximately what inference speedup was achieved using ONNX optimizations according to the paper?",
    "ground_truth": "Nearly 4× faster inference.",
    "difficulty": "medium",
    "category": "deployment"
  },
  {
    "id": "tr_q058",
    "question": "Which two deep learning frameworks are natively supported by the Transformers library?",
    "ground_truth": "PyTorch and TensorFlow.",
    "difficulty": "easy",
    "category": "frameworks"
  },
  {
    "id": "tr_q059",
    "question": "What is a major design philosophy of the Transformers library?",
    "ground_truth": "Providing a unified, extensible, and production-ready API for Transformer architectures and pretrained models.",
    "difficulty": "medium",
    "category": "design"
  },
  {
    "id": "tr_q060",
    "question": "What is the main conclusion of the paper?",
    "ground_truth": "Open-source infrastructure and model sharing are essential for democratizing access to state-of-the-art Transformer models and accelerating NLP research.",
    "difficulty": "medium",
    "category": "conclusion"
  },
  {
    "id": "tr_q061",
    "question": "What is the primary goal of the Reformer architecture?",
    "ground_truth": "To make Transformer models significantly more memory-efficient and computationally efficient for long sequences.",
    "difficulty": "easy",
    "category": "overview"
  },
  {
    "id": "tr_q062",
    "question": "What are the two main techniques introduced by Reformer?",
    "ground_truth": "Locality-Sensitive Hashing (LSH) Attention and Reversible Residual Layers.",
    "difficulty": "easy",
    "category": "architecture"
  },
  {
    "id": "tr_q063",
    "question": "What computational complexity does standard self-attention have with respect to sequence length L?",
    "ground_truth": "O(L²).",
    "difficulty": "easy",
    "category": "attention"
  },
  {
    "id": "tr_q064",
    "question": "What computational complexity does LSH Attention achieve?",
    "ground_truth": "O(L log L).",
    "difficulty": "easy",
    "category": "attention"
  },
  {
    "id": "tr_q065",
    "question": "Why does standard self-attention become expensive for long sequences?",
    "ground_truth": "Because every token attends to every other token, creating a quadratic attention matrix.",
    "difficulty": "easy",
    "category": "motivation"
  },
  {
    "id": "tr_q066",
    "question": "What is the core idea behind LSH Attention?",
    "ground_truth": "Tokens are hashed into buckets and attend primarily to other tokens in the same bucket.",
    "difficulty": "easy",
    "category": "attention"
  },
  {
    "id": "tr_q067",
    "question": "What property should a locality-sensitive hash function satisfy?",
    "ground_truth": "Similar vectors should have a high probability of being assigned to the same bucket.",
    "difficulty": "medium",
    "category": "attention"
  },
  {
    "id": "tr_q068",
    "question": "Why does Reformer share query and key projections?",
    "ground_truth": "To simplify LSH-based nearest-neighbor retrieval and ensure queries and keys are comparable.",
    "difficulty": "medium",
    "category": "architecture"
  },
  {
    "id": "tr_q069",
    "question": "What problem can occur with a shared query-key formulation if self-attention is left unchanged?",
    "ground_truth": "Tokens may strongly attend to themselves because their similarity score is maximal.",
    "difficulty": "medium",
    "category": "attention"
  },
  {
    "id": "tr_q070",
    "question": "How does Reformer address excessive self-attention in the shared QK setup?",
    "ground_truth": "By masking self-attention except when no other valid attention target exists.",
    "difficulty": "medium",
    "category": "attention"
  },
  {
    "id": "tr_q071",
    "question": "What is the purpose of multiple hashing rounds in LSH Attention?",
    "ground_truth": "To reduce the probability that similar tokens are separated into different buckets.",
    "difficulty": "medium",
    "category": "attention"
  },
  {
    "id": "tr_q072",
    "question": "What are Reversible Residual Layers designed to eliminate?",
    "ground_truth": "The need to store activations for every layer during backpropagation.",
    "difficulty": "easy",
    "category": "memory_efficiency"
  },
  {
    "id": "tr_q073",
    "question": "How do reversible layers reduce memory consumption?",
    "ground_truth": "Intermediate activations can be reconstructed during the backward pass instead of being stored.",
    "difficulty": "medium",
    "category": "memory_efficiency"
  },
  {
    "id": "tr_q074",
    "question": "What functions are used as the two reversible components in Reformer blocks?",
    "ground_truth": "Attention and Feed-Forward Network.",
    "difficulty": "easy",
    "category": "architecture"
  },
  {
    "id": "tr_q075",
    "question": "What additional memory-saving technique is applied to feed-forward layers?",
    "ground_truth": "Chunking activations into smaller pieces during computation.",
    "difficulty": "easy",
    "category": "memory_efficiency"
  },
  {
    "id": "tr_q076",
    "question": "Why is chunking particularly effective for feed-forward layers?",
    "ground_truth": "Because computations at different sequence positions are independent and can be processed separately.",
    "difficulty": "medium",
    "category": "optimization"
  },
  {
    "id": "tr_q077",
    "question": "Which benchmark was used to evaluate long-context language modeling performance?",
    "ground_truth": "enwik8 with sequence lengths up to 64K tokens.",
    "difficulty": "easy",
    "category": "evaluation"
  },
  {
    "id": "tr_q078",
    "question": "How did Reformer perform compared to standard Transformers in the experiments?",
    "ground_truth": "It achieved comparable performance while using substantially less memory and computation.",
    "difficulty": "easy",
    "category": "results"
  },
  {
    "id": "tr_q079",
    "question": "What is one major advantage of Reformer for long-sequence tasks?",
    "ground_truth": "It enables training and inference on very long sequences that would be impractical with standard attention.",
    "difficulty": "easy",
    "category": "applications"
  },
  {
    "id": "tr_q080",
    "question": "What is the main conclusion of the Reformer paper?",
    "ground_truth": "Efficient attention mechanisms and reversible layers can dramatically reduce Transformer memory and computational costs without sacrificing performance.",
    "difficulty": "easy",
    "category": "conclusion"
  },
  {
    "id": "tr_q081",
    "question": "What limitation of Vision Transformers (ViT) does TNT aim to address?",
    "ground_truth": "ViT models image patches as tokens but largely ignore the fine-grained structure inside each patch.",
    "difficulty": "easy",
    "category": "motivation"
  },
  {
    "id": "tr_q082",
    "question": "What does TNT stand for?",
    "ground_truth": "Transformer in Transformer.",
    "difficulty": "easy",
    "category": "overview"
  },
  {
    "id": "tr_q083",
    "question": "How does TNT interpret image patches?",
    "ground_truth": "As visual sentences composed of smaller visual words.",
    "difficulty": "easy",
    "category": "architecture"
  },
  {
    "id": "tr_q084",
    "question": "What are visual words in TNT?",
    "ground_truth": "Sub-patches obtained by further dividing each image patch.",
    "difficulty": "easy",
    "category": "architecture"
  },
  {
    "id": "tr_q085",
    "question": "What is the purpose of the inner transformer block in TNT?",
    "ground_truth": "To model relationships among visual words within a patch.",
    "difficulty": "easy",
    "category": "architecture"
  },
  {
    "id": "tr_q086",
    "question": "What is the purpose of the outer transformer block in TNT?",
    "ground_truth": "To model relationships among visual sentence embeddings across patches.",
    "difficulty": "easy",
    "category": "architecture"
  },
  {
    "id": "tr_q087",
    "question": "How does TNT incorporate word-level information into sentence-level representations?",
    "ground_truth": "Word embeddings are projected and added to the corresponding sentence embeddings.",
    "difficulty": "medium",
    "category": "architecture"
  },
  {
    "id": "tr_q088",
    "question": "What role does the class token play in TNT?",
    "ground_truth": "It serves as the final image representation used for classification.",
    "difficulty": "easy",
    "category": "architecture"
  },
  {
    "id": "tr_q089",
    "question": "Why does TNT introduce a second transformer inside each patch?",
    "ground_truth": "To capture local visual structure and fine-grained details that standard ViT misses.",
    "difficulty": "medium",
    "category": "motivation"
  },
  {
    "id": "tr_q090",
    "question": "What type of position encoding is used for sentence embeddings?",
    "ground_truth": "Learnable sentence position encodings.",
    "difficulty": "easy",
    "category": "position_encoding"
  },
  {
    "id": "tr_q091",
    "question": "What type of position encoding is used for visual words?",
    "ground_truth": "Learnable word position encodings shared across sentences.",
    "difficulty": "easy",
    "category": "position_encoding"
  },
  {
    "id": "tr_q092",
    "question": "What is the primary benefit of the inner transformer according to the paper?",
    "ground_truth": "Better preservation and modeling of local image information.",
    "difficulty": "easy",
    "category": "representation_learning"
  },
  {
    "id": "tr_q093",
    "question": "How many visual words per patch are used by default in TNT?",
    "ground_truth": "16 visual words.",
    "difficulty": "medium",
    "category": "architecture"
  },
  {
    "id": "tr_q094",
    "question": "What default patch size is used in TNT?",
    "ground_truth": "16×16 pixels.",
    "difficulty": "medium",
    "category": "architecture"
  },
  {
    "id": "tr_q095",
    "question": "What ImageNet top-1 accuracy does TNT-S achieve?",
    "ground_truth": "81.5% top-1 accuracy.",
    "difficulty": "medium",
    "category": "results"
  },
  {
    "id": "tr_q096",
    "question": "How much improvement does TNT-S achieve over DeiT-S on ImageNet?",
    "ground_truth": "Approximately 1.7 percentage points higher top-1 accuracy.",
    "difficulty": "medium",
    "category": "results"
  },
  {
    "id": "tr_q097",
    "question": "What happens when sentence-level and word-level position encodings are both removed?",
    "ground_truth": "ImageNet accuracy drops significantly compared to using both encodings.",
    "difficulty": "medium",
    "category": "ablation"
  },
  {
    "id": "tr_q098",
    "question": "What did feature-map visualizations reveal about TNT compared to DeiT?",
    "ground_truth": "TNT preserves richer local information and learns more diverse feature representations.",
    "difficulty": "medium",
    "category": "analysis"
  },
  {
    "id": "tr_q099",
    "question": "How does TNT perform on downstream tasks such as object detection and segmentation?",
    "ground_truth": "It consistently outperforms comparable transformer backbones while maintaining similar computational cost.",
    "difficulty": "medium",
    "category": "transfer_learning"
  },
  {
    "id": "tr_q100",
    "question": "What is the main conclusion of the TNT paper?",
    "ground_truth": "Modeling both patch-level and sub-patch-level relationships improves visual representation learning and yields better performance than standard Vision Transformers.",
    "difficulty": "easy",
    "category": "conclusion"
  }
]